todoer/__init__.py
todoer/__main__.py
todoer/todoer.py
todoer-0.1.1.dist-info/entry_points.txt
todoer-0.1.1.dist-info/LICENSE
todoer-0.1.1.dist-info/WHEEL
todoer-0.1.1.dist-info/METADATA
todoer-0.1.1.dist-info/RECORD
